{
  "timestamp": "2026-02-07T12:01:30.509062",
  "model": "medgemma-27b-text-it-mlx",
  "summary": [
    {
      "prompt_key": "baseline",
      "prompt_name": "Baseline (現行)",
      "total": 75,
      "correct": 57,
      "accuracy": 0.76,
      "avg_time": 1.1388555177052815,
      "errors": 0,
      "empty_responses": 0
    }
  ],
  "details": {
    "baseline": [
      {
        "problem_id": "116D1",
        "prediction": "c",
        "gold": "c",
        "correct": true,
        "response": "c",
        "time": 1.0302650928497314
      },
      {
        "problem_id": "116D2",
        "prediction": "a",
        "gold": "a",
        "correct": true,
        "response": "a",
        "time": 0.5710008144378662
      },
      {
        "problem_id": "116D3",
        "prediction": "c",
        "gold": "c",
        "correct": true,
        "response": "c",
        "time": 0.5322487354278564
      },
      {
        "problem_id": "116D4",
        "prediction": "d",
        "gold": "d",
        "correct": true,
        "response": "d",
        "time": 0.5065829753875732
      },
      {
        "problem_id": "116D5",
        "prediction": "b",
        "gold": "b",
        "correct": true,
        "response": "b",
        "time": 0.48879528045654297
      },
      {
        "problem_id": "116D6",
        "prediction": "c",
        "gold": "c",
        "correct": true,
        "response": "c",
        "time": 0.43643903732299805
      },
      {
        "problem_id": "116D7",
        "prediction": "d",
        "gold": "d",
        "correct": true,
        "response": "d",
        "time": 0.49389195442199707
      },
      {
        "problem_id": "116D8",
        "prediction": "e",
        "gold": "e",
        "correct": true,
        "response": "e",
        "time": 0.49034619331359863
      },
      {
        "problem_id": "116D9",
        "prediction": "c",
        "gold": "c",
        "correct": true,
        "response": "c",
        "time": 0.4954400062561035
      },
      {
        "problem_id": "116D10",
        "prediction": "d",
        "gold": "d",
        "correct": true,
        "response": "d",
        "time": 0.4868309497833252
      },
      {
        "problem_id": "116D11",
        "prediction": "d,e",
        "gold": "c,e",
        "correct": false,
        "response": "d,e",
        "time": 0.5441117286682129
      },
      {
        "problem_id": "116D12",
        "prediction": "b,c,d",
        "gold": "b,c,d",
        "correct": true,
        "response": "b,c,d",
        "time": 0.6310141086578369
      },
      {
        "problem_id": "116D13",
        "prediction": "a,b,c",
        "gold": "a,b,c",
        "correct": true,
        "response": "a,b,c",
        "time": 0.6303200721740723
      },
      {
        "problem_id": "116D14",
        "prediction": "b,c,d",
        "gold": "b,c,d",
        "correct": true,
        "response": "b,c,d",
        "time": 0.6559460163116455
      },
      {
        "problem_id": "116D15",
        "prediction": "a,b,d",
        "gold": "a,b,d",
        "correct": true,
        "response": "a,b,d",
        "time": 0.6422703266143799
      },
      {
        "problem_id": "116D16",
        "prediction": "a",
        "gold": "a",
        "correct": true,
        "response": "a",
        "time": 0.5837161540985107
      },
      {
        "problem_id": "116D17",
        "prediction": "b",
        "gold": "b",
        "correct": true,
        "response": "b",
        "time": 0.7905929088592529
      },
      {
        "problem_id": "116D18",
        "prediction": "a",
        "gold": "a",
        "correct": true,
        "response": "a",
        "time": 0.8685729503631592
      },
      {
        "problem_id": "116D19",
        "prediction": "c",
        "gold": "c",
        "correct": true,
        "response": "c",
        "time": 0.9451980590820312
      },
      {
        "problem_id": "116D20",
        "prediction": "d",
        "gold": "e",
        "correct": false,
        "response": "d",
        "time": 1.0175938606262207
      },
      {
        "problem_id": "116D21",
        "prediction": "c",
        "gold": "c",
        "correct": true,
        "response": "c",
        "time": 1.3995411396026611
      },
      {
        "problem_id": "116D22",
        "prediction": "a",
        "gold": "a",
        "correct": true,
        "response": "a",
        "time": 0.7078540325164795
      },
      {
        "problem_id": "116D23",
        "prediction": "a",
        "gold": "d",
        "correct": false,
        "response": "a",
        "time": 1.080298900604248
      },
      {
        "problem_id": "116D24",
        "prediction": "d",
        "gold": "d",
        "correct": true,
        "response": "d",
        "time": 1.3821070194244385
      },
      {
        "problem_id": "116D25",
        "prediction": "a",
        "gold": "a",
        "correct": true,
        "response": "a",
        "time": 1.241455078125
      },
      {
        "problem_id": "116D26",
        "prediction": "d",
        "gold": "d",
        "correct": true,
        "response": "d",
        "time": 0.7279348373413086
      },
      {
        "problem_id": "116D27",
        "prediction": "d",
        "gold": "e",
        "correct": false,
        "response": "d",
        "time": 1.1601228713989258
      },
      {
        "problem_id": "116D28",
        "prediction": "e",
        "gold": "e",
        "correct": true,
        "response": "e",
        "time": 0.724215030670166
      },
      {
        "problem_id": "116D29",
        "prediction": "a",
        "gold": "a",
        "correct": true,
        "response": "a",
        "time": 0.7159311771392822
      },
      {
        "problem_id": "116D30",
        "prediction": "a",
        "gold": "a",
        "correct": true,
        "response": "a",
        "time": 0.9285080432891846
      },
      {
        "problem_id": "116D31",
        "prediction": "e",
        "gold": "b",
        "correct": false,
        "response": "e",
        "time": 0.7958488464355469
      },
      {
        "problem_id": "116D32",
        "prediction": "c",
        "gold": "a",
        "correct": false,
        "response": "c",
        "time": 1.0813632011413574
      },
      {
        "problem_id": "116D33",
        "prediction": "d",
        "gold": "d",
        "correct": true,
        "response": "d",
        "time": 1.3981661796569824
      },
      {
        "problem_id": "116D34",
        "prediction": "b",
        "gold": "b",
        "correct": true,
        "response": "b",
        "time": 1.0026800632476807
      },
      {
        "problem_id": "116D35",
        "prediction": "d",
        "gold": "a",
        "correct": false,
        "response": "d",
        "time": 1.0170948505401611
      },
      {
        "problem_id": "116D36",
        "prediction": "a",
        "gold": "a",
        "correct": true,
        "response": "a",
        "time": 0.6387500762939453
      },
      {
        "problem_id": "116D37",
        "prediction": "c",
        "gold": "c",
        "correct": true,
        "response": "c",
        "time": 0.7085909843444824
      },
      {
        "problem_id": "116D38",
        "prediction": "b",
        "gold": "b",
        "correct": true,
        "response": "b",
        "time": 1.1473360061645508
      },
      {
        "problem_id": "116D39",
        "prediction": "d",
        "gold": "d",
        "correct": true,
        "response": "d",
        "time": 1.1508588790893555
      },
      {
        "problem_id": "116D40",
        "prediction": "d",
        "gold": "d",
        "correct": true,
        "response": "d",
        "time": 1.389232873916626
      },
      {
        "problem_id": "116D41",
        "prediction": "b",
        "gold": "b",
        "correct": true,
        "response": "b",
        "time": 1.2355871200561523
      },
      {
        "problem_id": "116D42",
        "prediction": "b",
        "gold": "b",
        "correct": true,
        "response": "b",
        "time": 1.2420620918273926
      },
      {
        "problem_id": "116D43",
        "prediction": "d",
        "gold": "d",
        "correct": true,
        "response": "d",
        "time": 0.8723907470703125
      },
      {
        "problem_id": "116D44",
        "prediction": "d",
        "gold": "d",
        "correct": true,
        "response": "d",
        "time": 1.59287691116333
      },
      {
        "problem_id": "116D45",
        "prediction": "e",
        "gold": "e",
        "correct": true,
        "response": "e",
        "time": 1.3112337589263916
      },
      {
        "problem_id": "116D46",
        "prediction": "c",
        "gold": "c",
        "correct": true,
        "response": "この問題は、画像診断（CTスキャン）の解釈と、それに基づいた適切な治療法の選択を問うています。\n\n**思考プロセス:**\n\n1.  **患者情報と症状の分析:**\n    *   72歳男性。\n    *   突然の激しい頭痛、急激な両側の視力低下。\n    *   意識清明。\n    *   高血圧（154/92mmHg）。\n    *   四肢麻痺なし。\n\n2.  **CT画像（冠状断像A、矢",
        "time": 15.327036142349243
      },
      {
        "problem_id": "116D47",
        "prediction": "c",
        "gold": "c",
        "correct": true,
        "response": "c",
        "time": 0.7279958724975586
      },
      {
        "problem_id": "116D48",
        "prediction": "c",
        "gold": "c",
        "correct": true,
        "response": "c",
        "time": 0.952326774597168
      },
      {
        "problem_id": "116D49",
        "prediction": "d",
        "gold": "e",
        "correct": false,
        "response": "d",
        "time": 1.7291879653930664
      },
      {
        "problem_id": "116D50",
        "prediction": "c",
        "gold": "c",
        "correct": true,
        "response": "c",
        "time": 1.6486561298370361
      },
      {
        "problem_id": "116D51",
        "prediction": "c",
        "gold": "c",
        "correct": true,
        "response": "c",
        "time": 1.0043201446533203
      },
      {
        "problem_id": "116D52",
        "prediction": "c",
        "gold": "a",
        "correct": false,
        "response": "c",
        "time": 0.9367609024047852
      },
      {
        "problem_id": "116D53",
        "prediction": "d",
        "gold": "d",
        "correct": true,
        "response": "d",
        "time": 1.0029470920562744
      },
      {
        "problem_id": "116D54",
        "prediction": "a",
        "gold": "a",
        "correct": true,
        "response": "a",
        "time": 0.6477701663970947
      },
      {
        "problem_id": "116D55",
        "prediction": "c",
        "gold": "d",
        "correct": false,
        "response": "c",
        "time": 1.2486672401428223
      },
      {
        "problem_id": "116D56",
        "prediction": "c",
        "gold": "c",
        "correct": true,
        "response": "c",
        "time": 1.0107090473175049
      },
      {
        "problem_id": "116D57",
        "prediction": "b",
        "gold": "b",
        "correct": true,
        "response": "b",
        "time": 0.7190279960632324
      },
      {
        "problem_id": "116D58",
        "prediction": "c",
        "gold": "a",
        "correct": false,
        "response": "c",
        "time": 0.8647890090942383
      },
      {
        "problem_id": "116D59",
        "prediction": "d",
        "gold": "d",
        "correct": true,
        "response": "d",
        "time": 1.013375997543335
      },
      {
        "problem_id": "116D60",
        "prediction": "d",
        "gold": "d",
        "correct": true,
        "response": "d",
        "time": 1.2942802906036377
      },
      {
        "problem_id": "116D61",
        "prediction": "e",
        "gold": "e",
        "correct": true,
        "response": "e",
        "time": 0.7835562229156494
      },
      {
        "problem_id": "116D62",
        "prediction": "d",
        "gold": "d",
        "correct": true,
        "response": "d",
        "time": 1.0080347061157227
      },
      {
        "problem_id": "116D63",
        "prediction": "a",
        "gold": "a",
        "correct": true,
        "response": "a",
        "time": 0.6519608497619629
      },
      {
        "problem_id": "116D64",
        "prediction": "d",
        "gold": "b",
        "correct": false,
        "response": "d",
        "time": 1.0101850032806396
      },
      {
        "problem_id": "116D65",
        "prediction": "d",
        "gold": "c",
        "correct": false,
        "response": "d",
        "time": 1.653487205505371
      },
      {
        "problem_id": "116D66",
        "prediction": "c,d",
        "gold": "b,d",
        "correct": false,
        "response": "c,d",
        "time": 0.9217510223388672
      },
      {
        "problem_id": "116D67",
        "prediction": "c,e",
        "gold": "c,e",
        "correct": true,
        "response": "c,e",
        "time": 0.8415400981903076
      },
      {
        "problem_id": "116D68",
        "prediction": "c,e",
        "gold": "c,e",
        "correct": true,
        "response": "c,e",
        "time": 0.7709269523620605
      },
      {
        "problem_id": "116D69",
        "prediction": "a,d",
        "gold": "c,d",
        "correct": false,
        "response": "a,d",
        "time": 1.4534227848052979
      },
      {
        "problem_id": "116D70",
        "prediction": "b,e",
        "gold": "b,e",
        "correct": true,
        "response": "b,e",
        "time": 0.7747559547424316
      },
      {
        "problem_id": "116D71",
        "prediction": "b,c",
        "gold": "a,b",
        "correct": false,
        "response": "b,c",
        "time": 0.8450639247894287
      },
      {
        "problem_id": "116D72",
        "prediction": "a,b,c",
        "gold": "a,b,e",
        "correct": false,
        "response": "a,b,c",
        "time": 0.9818620681762695
      },
      {
        "problem_id": "116D73",
        "prediction": "a,b,e",
        "gold": "a,b,e",
        "correct": true,
        "response": "a,b,e",
        "time": 1.2690951824188232
      },
      {
        "problem_id": "116D74",
        "prediction": "a,b,d",
        "gold": "a,b,d",
        "correct": true,
        "response": "a,b,d",
        "time": 1.1224372386932373
      },
      {
        "problem_id": "116D75",
        "prediction": "b,c,e",
        "gold": "a,b,e",
        "correct": false,
        "response": "b,c,e",
        "time": 1.7050158977508545
      }
    ]
  },
  "prompts": {
    "baseline": "あなたは医学の専門家です。選択肢から正解をa,b,c,d,eで答えてください。",
    "format_strict": "あなたは臨床医学に精通した医師です。\n問題を読み、正解の選択肢をアルファベット(a,b,c,d,e)のみで回答してください。\n複数選択の場合はカンマ区切りで回答してください。例: a,c\n余計な説明は不要です。",
    "chain_of_thought": "あなたは臨床医学に精通した医師です。\n\n回答手順:\n1. 問題文のキーワードを確認\n2. 各選択肢を医学的に検討\n3. 正解を選択\n\n最終行に「答え:」に続けて選択肢(a,b,c,d,e)のみを記載してください。",
    "japanese_medical": "あなたは日本の医療制度と臨床医学に精通した専門医です。\n医学の多肢選択問題に回答します。\n\n重要:\n- 日本の診療ガイドラインに基づいて判断\n- 選択肢はa,b,c,d,eのアルファベットで回答\n- 指定された個数を必ず選択\n\n回答形式: a または a,b,c（複数の場合）"
  }
}