{
  "timestamp": "2026-02-06T10:14:09.845117",
  "model": "mlx-community/llama-3.3-70b-instruct",
  "summary": [
    {
      "prompt_key": "baseline",
      "prompt_name": "Baseline (現行)",
      "total": 75,
      "correct": 51,
      "accuracy": 0.68,
      "avg_time": 2.138089714050293,
      "errors": 0,
      "empty_responses": 0
    },
    {
      "prompt_key": "format_strict",
      "prompt_name": "案A: 回答形式強化",
      "total": 75,
      "correct": 51,
      "accuracy": 0.68,
      "avg_time": 2.206135450998942,
      "errors": 0,
      "empty_responses": 0
    },
    {
      "prompt_key": "chain_of_thought",
      "prompt_name": "案B: 段階的思考",
      "total": 75,
      "correct": 51,
      "accuracy": 0.68,
      "avg_time": 2.332658093770345,
      "errors": 0,
      "empty_responses": 0
    },
    {
      "prompt_key": "japanese_medical",
      "prompt_name": "案C: 日本医療文脈",
      "total": 75,
      "correct": 50,
      "accuracy": 0.6666666666666666,
      "avg_time": 2.4367816829681397,
      "errors": 0,
      "empty_responses": 0
    }
  ],
  "details": {
    "baseline": [
      {
        "problem_id": "116A1",
        "prediction": "c",
        "gold": "c",
        "correct": true,
        "response": "c",
        "time": 3.138051748275757
      },
      {
        "problem_id": "116A2",
        "prediction": "c",
        "gold": "c",
        "correct": true,
        "response": "c",
        "time": 1.1974828243255615
      },
      {
        "problem_id": "116A3",
        "prediction": "b",
        "gold": "a",
        "correct": false,
        "response": "b",
        "time": 1.0309257507324219
      },
      {
        "problem_id": "116A4",
        "prediction": "d",
        "gold": "d",
        "correct": true,
        "response": "d",
        "time": 0.853579044342041
      },
      {
        "problem_id": "116A5",
        "prediction": "c",
        "gold": "c",
        "correct": true,
        "response": "c",
        "time": 1.020448923110962
      },
      {
        "problem_id": "116A6",
        "prediction": "e",
        "gold": "e",
        "correct": true,
        "response": "e",
        "time": 0.8561630249023438
      },
      {
        "problem_id": "116A7",
        "prediction": "d",
        "gold": "d",
        "correct": true,
        "response": "d",
        "time": 0.8722062110900879
      },
      {
        "problem_id": "116A8",
        "prediction": "d",
        "gold": "d",
        "correct": true,
        "response": "d",
        "time": 1.0364432334899902
      },
      {
        "problem_id": "116A9",
        "prediction": "b",
        "gold": "d",
        "correct": false,
        "response": "b",
        "time": 0.8626258373260498
      },
      {
        "problem_id": "116A10",
        "prediction": "c",
        "gold": "d",
        "correct": false,
        "response": "c",
        "time": 0.8554069995880127
      },
      {
        "problem_id": "116A11",
        "prediction": "e",
        "gold": "e",
        "correct": true,
        "response": "e",
        "time": 0.8627707958221436
      },
      {
        "problem_id": "116A12",
        "prediction": "e",
        "gold": "e",
        "correct": true,
        "response": "e",
        "time": 1.2090458869934082
      },
      {
        "problem_id": "116A13",
        "prediction": "b,e",
        "gold": "b,e",
        "correct": true,
        "response": "b,e",
        "time": 1.1231169700622559
      },
      {
        "problem_id": "116A14",
        "prediction": "c,d",
        "gold": "c,d",
        "correct": true,
        "response": "c,d",
        "time": 1.1222550868988037
      },
      {
        "problem_id": "116A15",
        "prediction": "c,e",
        "gold": "c,e",
        "correct": true,
        "response": "c,e",
        "time": 0.9271719455718994
      },
      {
        "problem_id": "116A16",
        "prediction": "e",
        "gold": "c",
        "correct": false,
        "response": "e",
        "time": 3.6838979721069336
      },
      {
        "problem_id": "116A17",
        "prediction": "d",
        "gold": "e",
        "correct": false,
        "response": "d",
        "time": 2.9975497722625732
      },
      {
        "problem_id": "116A18",
        "prediction": "a",
        "gold": "a",
        "correct": true,
        "response": "a",
        "time": 1.668468952178955
      },
      {
        "problem_id": "116A19",
        "prediction": "d",
        "gold": "d",
        "correct": true,
        "response": "d",
        "time": 2.614604949951172
      },
      {
        "problem_id": "116A20",
        "prediction": "b",
        "gold": "b",
        "correct": true,
        "response": "b",
        "time": 2.429072141647339
      },
      {
        "problem_id": "116A21",
        "prediction": "b",
        "gold": "c",
        "correct": false,
        "response": "b",
        "time": 2.8173422813415527
      },
      {
        "problem_id": "116A22",
        "prediction": "c",
        "gold": "c",
        "correct": true,
        "response": "c",
        "time": 1.400061845779419
      },
      {
        "problem_id": "116A23",
        "prediction": "e",
        "gold": "e",
        "correct": true,
        "response": "e",
        "time": 3.3825747966766357
      },
      {
        "problem_id": "116A24",
        "prediction": "a",
        "gold": "c",
        "correct": false,
        "response": "a",
        "time": 1.1985740661621094
      },
      {
        "problem_id": "116A25",
        "prediction": "a",
        "gold": "c",
        "correct": false,
        "response": "a",
        "time": 2.6734540462493896
      },
      {
        "problem_id": "116A26",
        "prediction": "e",
        "gold": "e",
        "correct": true,
        "response": "e",
        "time": 2.095289945602417
      },
      {
        "problem_id": "116A27",
        "prediction": "b",
        "gold": "b",
        "correct": true,
        "response": "b",
        "time": 2.79612398147583
      },
      {
        "problem_id": "116A28",
        "prediction": "a",
        "gold": "a",
        "correct": true,
        "response": "a",
        "time": 3.4844272136688232
      },
      {
        "problem_id": "116A29",
        "prediction": "a",
        "gold": "a",
        "correct": true,
        "response": "a",
        "time": 1.8247690200805664
      },
      {
        "problem_id": "116A30",
        "prediction": "c",
        "gold": "a",
        "correct": false,
        "response": "c",
        "time": 2.2551560401916504
      },
      {
        "problem_id": "116A31",
        "prediction": "c",
        "gold": "b",
        "correct": false,
        "response": "c",
        "time": 2.444854974746704
      },
      {
        "problem_id": "116A32",
        "prediction": "e",
        "gold": "e",
        "correct": true,
        "response": "e",
        "time": 2.066084146499634
      },
      {
        "problem_id": "116A33",
        "prediction": "e",
        "gold": "e",
        "correct": true,
        "response": "e",
        "time": 3.168977737426758
      },
      {
        "problem_id": "116A34",
        "prediction": "d",
        "gold": "a",
        "correct": false,
        "response": "d",
        "time": 1.6218340396881104
      },
      {
        "problem_id": "116A35",
        "prediction": "e",
        "gold": "e",
        "correct": true,
        "response": "e",
        "time": 2.8531341552734375
      },
      {
        "problem_id": "116A36",
        "prediction": "a",
        "gold": "a",
        "correct": true,
        "response": "a",
        "time": 3.628019094467163
      },
      {
        "problem_id": "116A37",
        "prediction": "c",
        "gold": "c",
        "correct": true,
        "response": "c",
        "time": 3.3704419136047363
      },
      {
        "problem_id": "116A38",
        "prediction": "e",
        "gold": "e",
        "correct": true,
        "response": "e",
        "time": 3.373295783996582
      },
      {
        "problem_id": "116A39",
        "prediction": "b",
        "gold": "b",
        "correct": true,
        "response": "b",
        "time": 1.8449890613555908
      },
      {
        "problem_id": "116A40",
        "prediction": "c",
        "gold": "b",
        "correct": false,
        "response": "c",
        "time": 3.791198968887329
      },
      {
        "problem_id": "116A41",
        "prediction": "e",
        "gold": "e",
        "correct": true,
        "response": "e",
        "time": 1.2033770084381104
      },
      {
        "problem_id": "116A42",
        "prediction": "a",
        "gold": "a",
        "correct": true,
        "response": "a",
        "time": 1.8222711086273193
      },
      {
        "problem_id": "116A43",
        "prediction": "c",
        "gold": "c",
        "correct": true,
        "response": "c",
        "time": 2.985185146331787
      },
      {
        "problem_id": "116A44",
        "prediction": "e",
        "gold": "e",
        "correct": true,
        "response": "e",
        "time": 2.0958259105682373
      },
      {
        "problem_id": "116A45",
        "prediction": "c",
        "gold": "d",
        "correct": false,
        "response": "c",
        "time": 1.2002549171447754
      },
      {
        "problem_id": "116A46",
        "prediction": "e",
        "gold": "b",
        "correct": false,
        "response": "e",
        "time": 2.112959146499634
      },
      {
        "problem_id": "116A47",
        "prediction": "e",
        "gold": "e",
        "correct": true,
        "response": "e",
        "time": 1.3983399868011475
      },
      {
        "problem_id": "116A48",
        "prediction": "e",
        "gold": "e",
        "correct": true,
        "response": "e",
        "time": 2.6417698860168457
      },
      {
        "problem_id": "116A49",
        "prediction": "a",
        "gold": "a",
        "correct": true,
        "response": "a",
        "time": 2.9803919792175293
      },
      {
        "problem_id": "116A50",
        "prediction": "a",
        "gold": "a",
        "correct": true,
        "response": "a",
        "time": 2.994112968444824
      },
      {
        "problem_id": "116A51",
        "prediction": "c",
        "gold": "c",
        "correct": true,
        "response": "c",
        "time": 2.069230079650879
      },
      {
        "problem_id": "116A52",
        "prediction": "d",
        "gold": "d",
        "correct": true,
        "response": "d",
        "time": 1.2000088691711426
      },
      {
        "problem_id": "116A53",
        "prediction": "b",
        "gold": "b",
        "correct": true,
        "response": "b",
        "time": 2.8242878913879395
      },
      {
        "problem_id": "116A54",
        "prediction": "c",
        "gold": "e",
        "correct": false,
        "response": "c",
        "time": 1.6320500373840332
      },
      {
        "problem_id": "116A55",
        "prediction": "e",
        "gold": "e",
        "correct": true,
        "response": "e",
        "time": 1.6611359119415283
      },
      {
        "problem_id": "116A56",
        "prediction": "b",
        "gold": "b",
        "correct": true,
        "response": "b",
        "time": 3.191817283630371
      },
      {
        "problem_id": "116A57",
        "prediction": "a",
        "gold": "a",
        "correct": true,
        "response": "a",
        "time": 2.2408688068389893
      },
      {
        "problem_id": "116A58",
        "prediction": "b",
        "gold": "b",
        "correct": true,
        "response": "b",
        "time": 1.3994879722595215
      },
      {
        "problem_id": "116A59",
        "prediction": "e",
        "gold": "c",
        "correct": false,
        "response": "e",
        "time": 1.6229848861694336
      },
      {
        "problem_id": "116A60",
        "prediction": "a",
        "gold": "a",
        "correct": true,
        "response": "a",
        "time": 1.6301779747009277
      },
      {
        "problem_id": "116A61",
        "prediction": "a",
        "gold": "a",
        "correct": true,
        "response": "a",
        "time": 1.406599998474121
      },
      {
        "problem_id": "116A62",
        "prediction": "e",
        "gold": "a",
        "correct": false,
        "response": "e",
        "time": 3.8043887615203857
      },
      {
        "problem_id": "116A63",
        "prediction": "c",
        "gold": "e",
        "correct": false,
        "response": "c",
        "time": 2.067967176437378
      },
      {
        "problem_id": "116A64",
        "prediction": "e",
        "gold": "e",
        "correct": true,
        "response": "e",
        "time": 2.0959312915802
      },
      {
        "problem_id": "116A65",
        "prediction": "b,e",
        "gold": "b,e",
        "correct": true,
        "response": "b,e",
        "time": 2.3075342178344727
      },
      {
        "problem_id": "116A66",
        "prediction": "a,d",
        "gold": "a,e",
        "correct": false,
        "response": "a, d",
        "time": 1.589655876159668
      },
      {
        "problem_id": "116A67",
        "prediction": "c,d",
        "gold": "a,d",
        "correct": false,
        "response": "d, c",
        "time": 2.3999621868133545
      },
      {
        "problem_id": "116A68",
        "prediction": "b,e",
        "gold": "d,e",
        "correct": false,
        "response": "b,e",
        "time": 2.4967620372772217
      },
      {
        "problem_id": "116A69",
        "prediction": "a,b",
        "gold": "a,b",
        "correct": true,
        "response": "a,b",
        "time": 1.6956100463867188
      },
      {
        "problem_id": "116A70",
        "prediction": "d,e",
        "gold": "b,e",
        "correct": false,
        "response": "d,e",
        "time": 3.5374391078948975
      },
      {
        "problem_id": "116A71",
        "prediction": "e",
        "gold": "e",
        "correct": true,
        "response": "e",
        "time": 2.118217945098877
      },
      {
        "problem_id": "116A72",
        "prediction": "a,b,c",
        "gold": "a,b,d",
        "correct": false,
        "response": "a,b,c",
        "time": 2.9092981815338135
      },
      {
        "problem_id": "116A73",
        "prediction": "c,d,e",
        "gold": "a,c,e",
        "correct": false,
        "response": "c,d,e",
        "time": 2.8073980808258057
      },
      {
        "problem_id": "116A74",
        "prediction": "a,b,d",
        "gold": "a,b,d",
        "correct": true,
        "response": "a,b,d",
        "time": 2.9642677307128906
      },
      {
        "problem_id": "116A75",
        "prediction": "a,c,d",
        "gold": "a,c,d",
        "correct": true,
        "response": "a,c,d",
        "time": 2.797266960144043
      }
    ],
    "format_strict": [
      {
        "problem_id": "116A1",
        "prediction": "c",
        "gold": "c",
        "correct": true,
        "response": "c",
        "time": 3.000680923461914
      },
      {
        "problem_id": "116A2",
        "prediction": "c",
        "gold": "c",
        "correct": true,
        "response": "c",
        "time": 1.197638988494873
      },
      {
        "problem_id": "116A3",
        "prediction": "b",
        "gold": "a",
        "correct": false,
        "response": "b",
        "time": 1.0310139656066895
      },
      {
        "problem_id": "116A4",
        "prediction": "d",
        "gold": "d",
        "correct": true,
        "response": "d",
        "time": 0.8658192157745361
      },
      {
        "problem_id": "116A5",
        "prediction": "c",
        "gold": "c",
        "correct": true,
        "response": "c",
        "time": 1.0630900859832764
      },
      {
        "problem_id": "116A6",
        "prediction": "e",
        "gold": "e",
        "correct": true,
        "response": "e",
        "time": 0.8552429676055908
      },
      {
        "problem_id": "116A7",
        "prediction": "d",
        "gold": "d",
        "correct": true,
        "response": "d",
        "time": 0.8599328994750977
      },
      {
        "problem_id": "116A8",
        "prediction": "d",
        "gold": "d",
        "correct": true,
        "response": "d",
        "time": 1.0336661338806152
      },
      {
        "problem_id": "116A9",
        "prediction": "e",
        "gold": "d",
        "correct": false,
        "response": "e",
        "time": 0.8518579006195068
      },
      {
        "problem_id": "116A10",
        "prediction": "c",
        "gold": "d",
        "correct": false,
        "response": "c",
        "time": 0.8651680946350098
      },
      {
        "problem_id": "116A11",
        "prediction": "e",
        "gold": "e",
        "correct": true,
        "response": "e",
        "time": 0.8665480613708496
      },
      {
        "problem_id": "116A12",
        "prediction": "e",
        "gold": "e",
        "correct": true,
        "response": "e",
        "time": 1.2012999057769775
      },
      {
        "problem_id": "116A13",
        "prediction": "b,e",
        "gold": "b,e",
        "correct": true,
        "response": "b,e",
        "time": 1.1045570373535156
      },
      {
        "problem_id": "116A14",
        "prediction": "c,d",
        "gold": "c,d",
        "correct": true,
        "response": "c,d",
        "time": 1.0998148918151855
      },
      {
        "problem_id": "116A15",
        "prediction": "c,e",
        "gold": "c,e",
        "correct": true,
        "response": "c,e",
        "time": 0.9277613162994385
      },
      {
        "problem_id": "116A16",
        "prediction": "e",
        "gold": "c",
        "correct": false,
        "response": "e",
        "time": 3.640821933746338
      },
      {
        "problem_id": "116A17",
        "prediction": "d",
        "gold": "e",
        "correct": false,
        "response": "d",
        "time": 2.9947941303253174
      },
      {
        "problem_id": "116A18",
        "prediction": "a",
        "gold": "a",
        "correct": true,
        "response": "a",
        "time": 1.6142468452453613
      },
      {
        "problem_id": "116A19",
        "prediction": "d",
        "gold": "d",
        "correct": true,
        "response": "d",
        "time": 2.633862018585205
      },
      {
        "problem_id": "116A20",
        "prediction": "b",
        "gold": "b",
        "correct": true,
        "response": "b",
        "time": 2.427483081817627
      },
      {
        "problem_id": "116A21",
        "prediction": "b",
        "gold": "c",
        "correct": false,
        "response": "b",
        "time": 2.809792995452881
      },
      {
        "problem_id": "116A22",
        "prediction": "c",
        "gold": "c",
        "correct": true,
        "response": "c",
        "time": 1.4228472709655762
      },
      {
        "problem_id": "116A23",
        "prediction": "e",
        "gold": "e",
        "correct": true,
        "response": "e",
        "time": 3.4139018058776855
      },
      {
        "problem_id": "116A24",
        "prediction": "a",
        "gold": "c",
        "correct": false,
        "response": "a",
        "time": 1.2051820755004883
      },
      {
        "problem_id": "116A25",
        "prediction": "b",
        "gold": "c",
        "correct": false,
        "response": "b",
        "time": 2.750248908996582
      },
      {
        "problem_id": "116A26",
        "prediction": "e",
        "gold": "e",
        "correct": true,
        "response": "e",
        "time": 2.085465908050537
      },
      {
        "problem_id": "116A27",
        "prediction": "b",
        "gold": "b",
        "correct": true,
        "response": "b",
        "time": 2.8479371070861816
      },
      {
        "problem_id": "116A28",
        "prediction": "a",
        "gold": "a",
        "correct": true,
        "response": "a",
        "time": 3.5216410160064697
      },
      {
        "problem_id": "116A29",
        "prediction": "a",
        "gold": "a",
        "correct": true,
        "response": "a",
        "time": 1.8671019077301025
      },
      {
        "problem_id": "116A30",
        "prediction": "c",
        "gold": "a",
        "correct": false,
        "response": "c",
        "time": 2.267512083053589
      },
      {
        "problem_id": "116A31",
        "prediction": "c",
        "gold": "b",
        "correct": false,
        "response": "c",
        "time": 2.438261032104492
      },
      {
        "problem_id": "116A32",
        "prediction": "e",
        "gold": "e",
        "correct": true,
        "response": "e",
        "time": 2.0838842391967773
      },
      {
        "problem_id": "116A33",
        "prediction": "e",
        "gold": "e",
        "correct": true,
        "response": "e",
        "time": 3.2486138343811035
      },
      {
        "problem_id": "116A34",
        "prediction": "d",
        "gold": "a",
        "correct": false,
        "response": "d",
        "time": 1.6075098514556885
      },
      {
        "problem_id": "116A35",
        "prediction": "e",
        "gold": "e",
        "correct": true,
        "response": "e",
        "time": 2.86087703704834
      },
      {
        "problem_id": "116A36",
        "prediction": "a",
        "gold": "a",
        "correct": true,
        "response": "a",
        "time": 3.7164406776428223
      },
      {
        "problem_id": "116A37",
        "prediction": "c",
        "gold": "c",
        "correct": true,
        "response": "c",
        "time": 3.6468708515167236
      },
      {
        "problem_id": "116A38",
        "prediction": "e",
        "gold": "e",
        "correct": true,
        "response": "e",
        "time": 3.6918368339538574
      },
      {
        "problem_id": "116A39",
        "prediction": "b",
        "gold": "b",
        "correct": true,
        "response": "b",
        "time": 1.9903898239135742
      },
      {
        "problem_id": "116A40",
        "prediction": "c",
        "gold": "b",
        "correct": false,
        "response": "c",
        "time": 4.258715867996216
      },
      {
        "problem_id": "116A41",
        "prediction": "e",
        "gold": "e",
        "correct": true,
        "response": "e",
        "time": 1.2930312156677246
      },
      {
        "problem_id": "116A42",
        "prediction": "a",
        "gold": "a",
        "correct": true,
        "response": "a",
        "time": 2.101012945175171
      },
      {
        "problem_id": "116A43",
        "prediction": "c",
        "gold": "c",
        "correct": true,
        "response": "c",
        "time": 3.3371880054473877
      },
      {
        "problem_id": "116A44",
        "prediction": "e",
        "gold": "e",
        "correct": true,
        "response": "e",
        "time": 2.152224063873291
      },
      {
        "problem_id": "116A45",
        "prediction": "c",
        "gold": "d",
        "correct": false,
        "response": "c",
        "time": 1.2077858448028564
      },
      {
        "problem_id": "116A46",
        "prediction": "e",
        "gold": "b",
        "correct": false,
        "response": "e",
        "time": 2.174870729446411
      },
      {
        "problem_id": "116A47",
        "prediction": "e",
        "gold": "e",
        "correct": true,
        "response": "e",
        "time": 1.4445350170135498
      },
      {
        "problem_id": "116A48",
        "prediction": "e",
        "gold": "e",
        "correct": true,
        "response": "e",
        "time": 2.773371934890747
      },
      {
        "problem_id": "116A49",
        "prediction": "a",
        "gold": "a",
        "correct": true,
        "response": "a",
        "time": 3.1564133167266846
      },
      {
        "problem_id": "116A50",
        "prediction": "a",
        "gold": "a",
        "correct": true,
        "response": "a",
        "time": 3.165578842163086
      },
      {
        "problem_id": "116A51",
        "prediction": "c",
        "gold": "c",
        "correct": true,
        "response": "c",
        "time": 2.1302878856658936
      },
      {
        "problem_id": "116A52",
        "prediction": "d",
        "gold": "d",
        "correct": true,
        "response": "d",
        "time": 1.2011229991912842
      },
      {
        "problem_id": "116A53",
        "prediction": "b",
        "gold": "b",
        "correct": true,
        "response": "b",
        "time": 2.977354049682617
      },
      {
        "problem_id": "116A54",
        "prediction": "c",
        "gold": "e",
        "correct": false,
        "response": "c",
        "time": 1.6736087799072266
      },
      {
        "problem_id": "116A55",
        "prediction": "e",
        "gold": "e",
        "correct": true,
        "response": "e",
        "time": 1.662140130996704
      },
      {
        "problem_id": "116A56",
        "prediction": "b",
        "gold": "b",
        "correct": true,
        "response": "b",
        "time": 3.3242969512939453
      },
      {
        "problem_id": "116A57",
        "prediction": "a",
        "gold": "a",
        "correct": true,
        "response": "a",
        "time": 2.3426313400268555
      },
      {
        "problem_id": "116A58",
        "prediction": "b",
        "gold": "b",
        "correct": true,
        "response": "b",
        "time": 1.4099352359771729
      },
      {
        "problem_id": "116A59",
        "prediction": "e",
        "gold": "c",
        "correct": false,
        "response": "e",
        "time": 1.6717209815979004
      },
      {
        "problem_id": "116A60",
        "prediction": "a",
        "gold": "a",
        "correct": true,
        "response": "a",
        "time": 1.6795949935913086
      },
      {
        "problem_id": "116A61",
        "prediction": "a",
        "gold": "a",
        "correct": true,
        "response": "a",
        "time": 1.471313714981079
      },
      {
        "problem_id": "116A62",
        "prediction": "e",
        "gold": "a",
        "correct": false,
        "response": "e",
        "time": 4.075825929641724
      },
      {
        "problem_id": "116A63",
        "prediction": "c",
        "gold": "e",
        "correct": false,
        "response": "c",
        "time": 2.179069995880127
      },
      {
        "problem_id": "116A64",
        "prediction": "e",
        "gold": "e",
        "correct": true,
        "response": "e",
        "time": 2.1831579208374023
      },
      {
        "problem_id": "116A65",
        "prediction": "b,e",
        "gold": "b,e",
        "correct": true,
        "response": "b,e",
        "time": 2.403078079223633
      },
      {
        "problem_id": "116A66",
        "prediction": "a,d",
        "gold": "a,e",
        "correct": false,
        "response": "a,d",
        "time": 1.5120949745178223
      },
      {
        "problem_id": "116A67",
        "prediction": "c,d",
        "gold": "a,d",
        "correct": false,
        "response": "d,c",
        "time": 2.4591522216796875
      },
      {
        "problem_id": "116A68",
        "prediction": "d,e",
        "gold": "d,e",
        "correct": true,
        "response": "d,e",
        "time": 2.6492860317230225
      },
      {
        "problem_id": "116A69",
        "prediction": "a,b",
        "gold": "a,b",
        "correct": true,
        "response": "a,b",
        "time": 1.7778232097625732
      },
      {
        "problem_id": "116A70",
        "prediction": "d,e",
        "gold": "b,e",
        "correct": false,
        "response": "d,e",
        "time": 3.8068690299987793
      },
      {
        "problem_id": "116A71",
        "prediction": "e",
        "gold": "e",
        "correct": true,
        "response": "e",
        "time": 2.1879889965057373
      },
      {
        "problem_id": "116A72",
        "prediction": "a,b,c",
        "gold": "a,b,d",
        "correct": false,
        "response": "a,b,c",
        "time": 3.092254877090454
      },
      {
        "problem_id": "116A73",
        "prediction": "c,d,e",
        "gold": "a,c,e",
        "correct": false,
        "response": "c,d,e",
        "time": 2.9135220050811768
      },
      {
        "problem_id": "116A74",
        "prediction": "a,d,e",
        "gold": "a,b,d",
        "correct": false,
        "response": "a,d,e",
        "time": 3.0805110931396484
      },
      {
        "problem_id": "116A75",
        "prediction": "a,c,d",
        "gold": "a,c,d",
        "correct": true,
        "response": "a,c,d",
        "time": 2.9191739559173584
      }
    ],
    "chain_of_thought": [
      {
        "problem_id": "116A1",
        "prediction": "c",
        "gold": "c",
        "correct": true,
        "response": "c",
        "time": 3.1772947311401367
      },
      {
        "problem_id": "116A2",
        "prediction": "c",
        "gold": "c",
        "correct": true,
        "response": "c",
        "time": 1.2187879085540771
      },
      {
        "problem_id": "116A3",
        "prediction": "b",
        "gold": "a",
        "correct": false,
        "response": "b",
        "time": 1.0381801128387451
      },
      {
        "problem_id": "116A4",
        "prediction": "d",
        "gold": "d",
        "correct": true,
        "response": "d",
        "time": 0.8688230514526367
      },
      {
        "problem_id": "116A5",
        "prediction": "c",
        "gold": "c",
        "correct": true,
        "response": "c",
        "time": 1.0444631576538086
      },
      {
        "problem_id": "116A6",
        "prediction": "e",
        "gold": "e",
        "correct": true,
        "response": "e",
        "time": 0.8646249771118164
      },
      {
        "problem_id": "116A7",
        "prediction": "d",
        "gold": "d",
        "correct": true,
        "response": "d",
        "time": 0.8618640899658203
      },
      {
        "problem_id": "116A8",
        "prediction": "d",
        "gold": "d",
        "correct": true,
        "response": "d",
        "time": 1.0386476516723633
      },
      {
        "problem_id": "116A9",
        "prediction": "b",
        "gold": "d",
        "correct": false,
        "response": "b",
        "time": 0.8615260124206543
      },
      {
        "problem_id": "116A10",
        "prediction": "c",
        "gold": "d",
        "correct": false,
        "response": "c",
        "time": 0.8845000267028809
      },
      {
        "problem_id": "116A11",
        "prediction": "e",
        "gold": "e",
        "correct": true,
        "response": "e",
        "time": 0.8589987754821777
      },
      {
        "problem_id": "116A12",
        "prediction": "e",
        "gold": "e",
        "correct": true,
        "response": "e",
        "time": 1.2225401401519775
      },
      {
        "problem_id": "116A13",
        "prediction": "b,e",
        "gold": "b,e",
        "correct": true,
        "response": "b,e",
        "time": 1.1180846691131592
      },
      {
        "problem_id": "116A14",
        "prediction": "c,d",
        "gold": "c,d",
        "correct": true,
        "response": "c,d",
        "time": 1.121279001235962
      },
      {
        "problem_id": "116A15",
        "prediction": "c,e",
        "gold": "c,e",
        "correct": true,
        "response": "c,e",
        "time": 0.9369430541992188
      },
      {
        "problem_id": "116A16",
        "prediction": "e",
        "gold": "c",
        "correct": false,
        "response": "e",
        "time": 4.0458738803863525
      },
      {
        "problem_id": "116A17",
        "prediction": "d",
        "gold": "e",
        "correct": false,
        "response": "d",
        "time": 3.272573947906494
      },
      {
        "problem_id": "116A18",
        "prediction": "a",
        "gold": "a",
        "correct": true,
        "response": "a",
        "time": 1.6964290142059326
      },
      {
        "problem_id": "116A19",
        "prediction": "d",
        "gold": "d",
        "correct": true,
        "response": "d",
        "time": 2.847532033920288
      },
      {
        "problem_id": "116A20",
        "prediction": "b",
        "gold": "b",
        "correct": true,
        "response": "b",
        "time": 2.623384952545166
      },
      {
        "problem_id": "116A21",
        "prediction": "b",
        "gold": "c",
        "correct": false,
        "response": "b",
        "time": 3.080904960632324
      },
      {
        "problem_id": "116A22",
        "prediction": "c",
        "gold": "c",
        "correct": true,
        "response": "c",
        "time": 1.428278923034668
      },
      {
        "problem_id": "116A23",
        "prediction": "e",
        "gold": "e",
        "correct": true,
        "response": "e",
        "time": 3.711534023284912
      },
      {
        "problem_id": "116A24",
        "prediction": "a",
        "gold": "c",
        "correct": false,
        "response": "a",
        "time": 1.2182080745697021
      },
      {
        "problem_id": "116A25",
        "prediction": "b",
        "gold": "c",
        "correct": false,
        "response": "b",
        "time": 2.8809421062469482
      },
      {
        "problem_id": "116A26",
        "prediction": "e",
        "gold": "e",
        "correct": true,
        "response": "e",
        "time": 2.216283082962036
      },
      {
        "problem_id": "116A27",
        "prediction": "b",
        "gold": "b",
        "correct": true,
        "response": "b",
        "time": 3.0565030574798584
      },
      {
        "problem_id": "116A28",
        "prediction": "a",
        "gold": "a",
        "correct": true,
        "response": "a",
        "time": 3.7687132358551025
      },
      {
        "problem_id": "116A29",
        "prediction": "a",
        "gold": "a",
        "correct": true,
        "response": "a",
        "time": 2.036626100540161
      },
      {
        "problem_id": "116A30",
        "prediction": "c",
        "gold": "a",
        "correct": false,
        "response": "c",
        "time": 2.444782257080078
      },
      {
        "problem_id": "116A31",
        "prediction": "c",
        "gold": "b",
        "correct": false,
        "response": "c",
        "time": 2.674910068511963
      },
      {
        "problem_id": "116A32",
        "prediction": "e",
        "gold": "e",
        "correct": true,
        "response": "e",
        "time": 2.2270572185516357
      },
      {
        "problem_id": "116A33",
        "prediction": "e",
        "gold": "e",
        "correct": true,
        "response": "e",
        "time": 3.4882469177246094
      },
      {
        "problem_id": "116A34",
        "prediction": "d",
        "gold": "a",
        "correct": false,
        "response": "d",
        "time": 1.7101497650146484
      },
      {
        "problem_id": "116A35",
        "prediction": "e",
        "gold": "e",
        "correct": true,
        "response": "e",
        "time": 3.1095168590545654
      },
      {
        "problem_id": "116A36",
        "prediction": "a",
        "gold": "a",
        "correct": true,
        "response": "a",
        "time": 3.9857118129730225
      },
      {
        "problem_id": "116A37",
        "prediction": "c",
        "gold": "c",
        "correct": true,
        "response": "c",
        "time": 3.7573049068450928
      },
      {
        "problem_id": "116A38",
        "prediction": "e",
        "gold": "e",
        "correct": true,
        "response": "e",
        "time": 3.6778953075408936
      },
      {
        "problem_id": "116A39",
        "prediction": "b",
        "gold": "b",
        "correct": true,
        "response": "b",
        "time": 1.9800200462341309
      },
      {
        "problem_id": "116A40",
        "prediction": "c",
        "gold": "b",
        "correct": false,
        "response": "c",
        "time": 4.2434587478637695
      },
      {
        "problem_id": "116A41",
        "prediction": "e",
        "gold": "e",
        "correct": true,
        "response": "e",
        "time": 1.301664113998413
      },
      {
        "problem_id": "116A42",
        "prediction": "a",
        "gold": "a",
        "correct": true,
        "response": "a",
        "time": 2.097608804702759
      },
      {
        "problem_id": "116A43",
        "prediction": "c",
        "gold": "c",
        "correct": true,
        "response": "c",
        "time": 3.3550772666931152
      },
      {
        "problem_id": "116A44",
        "prediction": "e",
        "gold": "e",
        "correct": true,
        "response": "e",
        "time": 2.245051860809326
      },
      {
        "problem_id": "116A45",
        "prediction": "c",
        "gold": "d",
        "correct": false,
        "response": "c",
        "time": 1.2462079524993896
      },
      {
        "problem_id": "116A46",
        "prediction": "e",
        "gold": "b",
        "correct": false,
        "response": "e",
        "time": 2.3145618438720703
      },
      {
        "problem_id": "116A47",
        "prediction": "e",
        "gold": "e",
        "correct": true,
        "response": "e",
        "time": 1.5489892959594727
      },
      {
        "problem_id": "116A48",
        "prediction": "e",
        "gold": "e",
        "correct": true,
        "response": "e",
        "time": 2.9430410861968994
      },
      {
        "problem_id": "116A49",
        "prediction": "a",
        "gold": "a",
        "correct": true,
        "response": "a",
        "time": 3.3519811630249023
      },
      {
        "problem_id": "116A50",
        "prediction": "a",
        "gold": "a",
        "correct": true,
        "response": "a",
        "time": 3.3053178787231445
      },
      {
        "problem_id": "116A51",
        "prediction": "c",
        "gold": "c",
        "correct": true,
        "response": "c",
        "time": 2.2692370414733887
      },
      {
        "problem_id": "116A52",
        "prediction": "d",
        "gold": "d",
        "correct": true,
        "response": "d",
        "time": 1.2542710304260254
      },
      {
        "problem_id": "116A53",
        "prediction": "b",
        "gold": "b",
        "correct": true,
        "response": "b",
        "time": 3.2081079483032227
      },
      {
        "problem_id": "116A54",
        "prediction": "c",
        "gold": "e",
        "correct": false,
        "response": "c",
        "time": 1.740401029586792
      },
      {
        "problem_id": "116A55",
        "prediction": "e",
        "gold": "e",
        "correct": true,
        "response": "e",
        "time": 1.8041532039642334
      },
      {
        "problem_id": "116A56",
        "prediction": "b",
        "gold": "b",
        "correct": true,
        "response": "b",
        "time": 3.620790958404541
      },
      {
        "problem_id": "116A57",
        "prediction": "a",
        "gold": "a",
        "correct": true,
        "response": "a",
        "time": 2.4926300048828125
      },
      {
        "problem_id": "116A58",
        "prediction": "b",
        "gold": "b",
        "correct": true,
        "response": "b",
        "time": 1.519577980041504
      },
      {
        "problem_id": "116A59",
        "prediction": "e",
        "gold": "c",
        "correct": false,
        "response": "e",
        "time": 1.8003640174865723
      },
      {
        "problem_id": "116A60",
        "prediction": "a",
        "gold": "a",
        "correct": true,
        "response": "a",
        "time": 1.8636128902435303
      },
      {
        "problem_id": "116A61",
        "prediction": "a",
        "gold": "a",
        "correct": true,
        "response": "a",
        "time": 1.5746629238128662
      },
      {
        "problem_id": "116A62",
        "prediction": "e",
        "gold": "a",
        "correct": false,
        "response": "e",
        "time": 4.370007038116455
      },
      {
        "problem_id": "116A63",
        "prediction": "c",
        "gold": "e",
        "correct": false,
        "response": "c",
        "time": 2.347968101501465
      },
      {
        "problem_id": "116A64",
        "prediction": "e",
        "gold": "e",
        "correct": true,
        "response": "e",
        "time": 2.3224120140075684
      },
      {
        "problem_id": "116A65",
        "prediction": "b,e",
        "gold": "b,e",
        "correct": true,
        "response": "b,e",
        "time": 2.5859909057617188
      },
      {
        "problem_id": "116A66",
        "prediction": "a,b",
        "gold": "a,e",
        "correct": false,
        "response": "a,b",
        "time": 1.6163909435272217
      },
      {
        "problem_id": "116A67",
        "prediction": "c,d",
        "gold": "a,d",
        "correct": false,
        "response": "d, c",
        "time": 2.7007651329040527
      },
      {
        "problem_id": "116A68",
        "prediction": "b,e",
        "gold": "d,e",
        "correct": false,
        "response": "b,e",
        "time": 2.8533151149749756
      },
      {
        "problem_id": "116A69",
        "prediction": "a,b",
        "gold": "a,b",
        "correct": true,
        "response": "a,b",
        "time": 1.8373868465423584
      },
      {
        "problem_id": "116A70",
        "prediction": "d,e",
        "gold": "b,e",
        "correct": false,
        "response": "d,e",
        "time": 4.0396411418914795
      },
      {
        "problem_id": "116A71",
        "prediction": "e",
        "gold": "e",
        "correct": true,
        "response": "e",
        "time": 2.3178977966308594
      },
      {
        "problem_id": "116A72",
        "prediction": "a,b,c",
        "gold": "a,b,d",
        "correct": false,
        "response": "a,b,c",
        "time": 3.3241958618164062
      },
      {
        "problem_id": "116A73",
        "prediction": "c,d,e",
        "gold": "a,c,e",
        "correct": false,
        "response": "c,d,e",
        "time": 3.0692150592803955
      },
      {
        "problem_id": "116A74",
        "prediction": "a,b,d",
        "gold": "a,b,d",
        "correct": true,
        "response": "a,b,d",
        "time": 3.3146111965179443
      },
      {
        "problem_id": "116A75",
        "prediction": "a,c,d",
        "gold": "a,c,d",
        "correct": true,
        "response": "a,c,d",
        "time": 3.092850923538208
      }
    ],
    "japanese_medical": [
      {
        "problem_id": "116A1",
        "prediction": "c",
        "gold": "c",
        "correct": true,
        "response": "c",
        "time": 3.605185031890869
      },
      {
        "problem_id": "116A2",
        "prediction": "c",
        "gold": "c",
        "correct": true,
        "response": "c",
        "time": 1.2521419525146484
      },
      {
        "problem_id": "116A3",
        "prediction": "b",
        "gold": "a",
        "correct": false,
        "response": "b",
        "time": 1.0823581218719482
      },
      {
        "problem_id": "116A4",
        "prediction": "d",
        "gold": "d",
        "correct": true,
        "response": "d",
        "time": 0.8959050178527832
      },
      {
        "problem_id": "116A5",
        "prediction": "c",
        "gold": "c",
        "correct": true,
        "response": "c",
        "time": 1.1080749034881592
      },
      {
        "problem_id": "116A6",
        "prediction": "e",
        "gold": "e",
        "correct": true,
        "response": "e",
        "time": 0.8999969959259033
      },
      {
        "problem_id": "116A7",
        "prediction": "d",
        "gold": "d",
        "correct": true,
        "response": "d",
        "time": 0.8951287269592285
      },
      {
        "problem_id": "116A8",
        "prediction": "d",
        "gold": "d",
        "correct": true,
        "response": "d",
        "time": 1.1112780570983887
      },
      {
        "problem_id": "116A9",
        "prediction": "b",
        "gold": "d",
        "correct": false,
        "response": "b",
        "time": 0.9007840156555176
      },
      {
        "problem_id": "116A10",
        "prediction": "c",
        "gold": "d",
        "correct": false,
        "response": "c",
        "time": 0.9061150550842285
      },
      {
        "problem_id": "116A11",
        "prediction": "e",
        "gold": "e",
        "correct": true,
        "response": "e",
        "time": 0.9039192199707031
      },
      {
        "problem_id": "116A12",
        "prediction": "e",
        "gold": "e",
        "correct": true,
        "response": "e",
        "time": 1.3347108364105225
      },
      {
        "problem_id": "116A13",
        "prediction": "b,e",
        "gold": "b,e",
        "correct": true,
        "response": "b,e",
        "time": 1.1957199573516846
      },
      {
        "problem_id": "116A14",
        "prediction": "c,d",
        "gold": "c,d",
        "correct": true,
        "response": "c,d",
        "time": 1.2176029682159424
      },
      {
        "problem_id": "116A15",
        "prediction": "c,e",
        "gold": "c,e",
        "correct": true,
        "response": "c,e",
        "time": 0.9659311771392822
      },
      {
        "problem_id": "116A16",
        "prediction": "e",
        "gold": "c",
        "correct": false,
        "response": "e",
        "time": 4.312588930130005
      },
      {
        "problem_id": "116A17",
        "prediction": "d",
        "gold": "e",
        "correct": false,
        "response": "d",
        "time": 3.460719108581543
      },
      {
        "problem_id": "116A18",
        "prediction": "a",
        "gold": "a",
        "correct": true,
        "response": "a",
        "time": 1.793962001800537
      },
      {
        "problem_id": "116A19",
        "prediction": "d",
        "gold": "d",
        "correct": true,
        "response": "d",
        "time": 3.0290310382843018
      },
      {
        "problem_id": "116A20",
        "prediction": "b",
        "gold": "b",
        "correct": true,
        "response": "b",
        "time": 2.7676870822906494
      },
      {
        "problem_id": "116A21",
        "prediction": "b",
        "gold": "c",
        "correct": false,
        "response": "b",
        "time": 3.2315688133239746
      },
      {
        "problem_id": "116A22",
        "prediction": "c",
        "gold": "c",
        "correct": true,
        "response": "c",
        "time": 1.5674748420715332
      },
      {
        "problem_id": "116A23",
        "prediction": "a",
        "gold": "e",
        "correct": false,
        "response": "a",
        "time": 3.911855936050415
      },
      {
        "problem_id": "116A24",
        "prediction": "a",
        "gold": "c",
        "correct": false,
        "response": "a",
        "time": 1.262511968612671
      },
      {
        "problem_id": "116A25",
        "prediction": "b",
        "gold": "c",
        "correct": false,
        "response": "b",
        "time": 3.0545406341552734
      },
      {
        "problem_id": "116A26",
        "prediction": "e",
        "gold": "e",
        "correct": true,
        "response": "e",
        "time": 2.3395400047302246
      },
      {
        "problem_id": "116A27",
        "prediction": "b",
        "gold": "b",
        "correct": true,
        "response": "b",
        "time": 3.212311029434204
      },
      {
        "problem_id": "116A28",
        "prediction": "a",
        "gold": "a",
        "correct": true,
        "response": "a",
        "time": 3.973560094833374
      },
      {
        "problem_id": "116A29",
        "prediction": "a",
        "gold": "a",
        "correct": true,
        "response": "a",
        "time": 2.155716896057129
      },
      {
        "problem_id": "116A30",
        "prediction": "c",
        "gold": "a",
        "correct": false,
        "response": "c",
        "time": 2.5616090297698975
      },
      {
        "problem_id": "116A31",
        "prediction": "c",
        "gold": "b",
        "correct": false,
        "response": "c",
        "time": 2.811640739440918
      },
      {
        "problem_id": "116A32",
        "prediction": "e",
        "gold": "e",
        "correct": true,
        "response": "e",
        "time": 2.3154046535491943
      },
      {
        "problem_id": "116A33",
        "prediction": "e",
        "gold": "e",
        "correct": true,
        "response": "e",
        "time": 3.7015788555145264
      },
      {
        "problem_id": "116A34",
        "prediction": "d",
        "gold": "a",
        "correct": false,
        "response": "d",
        "time": 1.7984287738800049
      },
      {
        "problem_id": "116A35",
        "prediction": "e",
        "gold": "e",
        "correct": true,
        "response": "e",
        "time": 3.270806074142456
      },
      {
        "problem_id": "116A36",
        "prediction": "a",
        "gold": "a",
        "correct": true,
        "response": "a",
        "time": 4.224539041519165
      },
      {
        "problem_id": "116A37",
        "prediction": "c",
        "gold": "c",
        "correct": true,
        "response": "c",
        "time": 3.956089735031128
      },
      {
        "problem_id": "116A38",
        "prediction": "e",
        "gold": "e",
        "correct": true,
        "response": "e",
        "time": 3.8557162284851074
      },
      {
        "problem_id": "116A39",
        "prediction": "b",
        "gold": "b",
        "correct": true,
        "response": "b",
        "time": 2.054621934890747
      },
      {
        "problem_id": "116A40",
        "prediction": "c",
        "gold": "b",
        "correct": false,
        "response": "c",
        "time": 4.455538034439087
      },
      {
        "problem_id": "116A41",
        "prediction": "e",
        "gold": "e",
        "correct": true,
        "response": "e",
        "time": 1.3291921615600586
      },
      {
        "problem_id": "116A42",
        "prediction": "a",
        "gold": "a",
        "correct": true,
        "response": "a",
        "time": 2.2204461097717285
      },
      {
        "problem_id": "116A43",
        "prediction": "c",
        "gold": "c",
        "correct": true,
        "response": "c",
        "time": 3.5273401737213135
      },
      {
        "problem_id": "116A44",
        "prediction": "e",
        "gold": "e",
        "correct": true,
        "response": "e",
        "time": 2.345107078552246
      },
      {
        "problem_id": "116A45",
        "prediction": "c",
        "gold": "d",
        "correct": false,
        "response": "c",
        "time": 1.3189678192138672
      },
      {
        "problem_id": "116A46",
        "prediction": "e",
        "gold": "b",
        "correct": false,
        "response": "e",
        "time": 2.4880950450897217
      },
      {
        "problem_id": "116A47",
        "prediction": "e",
        "gold": "e",
        "correct": true,
        "response": "e",
        "time": 1.6449790000915527
      },
      {
        "problem_id": "116A48",
        "prediction": "e",
        "gold": "e",
        "correct": true,
        "response": "e",
        "time": 3.0674731731414795
      },
      {
        "problem_id": "116A49",
        "prediction": "a",
        "gold": "a",
        "correct": true,
        "response": "a",
        "time": 3.4520559310913086
      },
      {
        "problem_id": "116A50",
        "prediction": "a",
        "gold": "a",
        "correct": true,
        "response": "a",
        "time": 3.464354991912842
      },
      {
        "problem_id": "116A51",
        "prediction": "c",
        "gold": "c",
        "correct": true,
        "response": "c",
        "time": 2.3601980209350586
      },
      {
        "problem_id": "116A52",
        "prediction": "d",
        "gold": "d",
        "correct": true,
        "response": "d",
        "time": 1.3015480041503906
      },
      {
        "problem_id": "116A53",
        "prediction": "b",
        "gold": "b",
        "correct": true,
        "response": "b",
        "time": 3.3383162021636963
      },
      {
        "problem_id": "116A54",
        "prediction": "c",
        "gold": "e",
        "correct": false,
        "response": "c",
        "time": 1.789233922958374
      },
      {
        "problem_id": "116A55",
        "prediction": "e",
        "gold": "e",
        "correct": true,
        "response": "e",
        "time": 1.8581998348236084
      },
      {
        "problem_id": "116A56",
        "prediction": "b",
        "gold": "b",
        "correct": true,
        "response": "b",
        "time": 3.734983205795288
      },
      {
        "problem_id": "116A57",
        "prediction": "a",
        "gold": "a",
        "correct": true,
        "response": "a",
        "time": 2.536875009536743
      },
      {
        "problem_id": "116A58",
        "prediction": "b",
        "gold": "b",
        "correct": true,
        "response": "b",
        "time": 1.6135530471801758
      },
      {
        "problem_id": "116A59",
        "prediction": "e",
        "gold": "c",
        "correct": false,
        "response": "e",
        "time": 1.8627221584320068
      },
      {
        "problem_id": "116A60",
        "prediction": "a",
        "gold": "a",
        "correct": true,
        "response": "a",
        "time": 1.8963408470153809
      },
      {
        "problem_id": "116A61",
        "prediction": "a",
        "gold": "a",
        "correct": true,
        "response": "a",
        "time": 1.6087207794189453
      },
      {
        "problem_id": "116A62",
        "prediction": "e",
        "gold": "a",
        "correct": false,
        "response": "e",
        "time": 4.505129098892212
      },
      {
        "problem_id": "116A63",
        "prediction": "c",
        "gold": "e",
        "correct": false,
        "response": "c",
        "time": 2.3949990272521973
      },
      {
        "problem_id": "116A64",
        "prediction": "e",
        "gold": "e",
        "correct": true,
        "response": "e",
        "time": 2.39542818069458
      },
      {
        "problem_id": "116A65",
        "prediction": "b,e",
        "gold": "b,e",
        "correct": true,
        "response": "b,e",
        "time": 2.622148036956787
      },
      {
        "problem_id": "116A66",
        "prediction": "a,b",
        "gold": "a,e",
        "correct": false,
        "response": "a,b",
        "time": 1.667253017425537
      },
      {
        "problem_id": "116A67",
        "prediction": "c,d",
        "gold": "a,d",
        "correct": false,
        "response": "d, c",
        "time": 2.7768540382385254
      },
      {
        "problem_id": "116A68",
        "prediction": "b,d",
        "gold": "d,e",
        "correct": false,
        "response": "b,d",
        "time": 2.869030237197876
      },
      {
        "problem_id": "116A69",
        "prediction": "a,b",
        "gold": "a,b",
        "correct": true,
        "response": "a,b",
        "time": 1.9069147109985352
      },
      {
        "problem_id": "116A70",
        "prediction": "d,e",
        "gold": "b,e",
        "correct": false,
        "response": "d,e",
        "time": 4.12720799446106
      },
      {
        "problem_id": "116A71",
        "prediction": "e",
        "gold": "e",
        "correct": true,
        "response": "e",
        "time": 2.380621910095215
      },
      {
        "problem_id": "116A72",
        "prediction": "a,b,c",
        "gold": "a,b,d",
        "correct": false,
        "response": "a,b,c",
        "time": 3.36413311958313
      },
      {
        "problem_id": "116A73",
        "prediction": "c,d,e",
        "gold": "a,c,e",
        "correct": false,
        "response": "c,d,e",
        "time": 3.1607189178466797
      },
      {
        "problem_id": "116A74",
        "prediction": "a,b,d",
        "gold": "a,b,d",
        "correct": true,
        "response": "a,b,d",
        "time": 3.3494019508361816
      },
      {
        "problem_id": "116A75",
        "prediction": "a,c,d",
        "gold": "a,c,d",
        "correct": true,
        "response": "a,c,d",
        "time": 3.126189947128296
      }
    ]
  },
  "prompts": {
    "baseline": "あなたは医学の専門家です。選択肢から正解をa,b,c,d,eで答えてください。",
    "format_strict": "あなたは臨床医学に精通した医師です。\n問題を読み、正解の選択肢をアルファベット(a,b,c,d,e)のみで回答してください。\n複数選択の場合はカンマ区切りで回答してください。例: a,c\n余計な説明は不要です。",
    "chain_of_thought": "あなたは臨床医学に精通した医師です。\n\n回答手順:\n1. 問題文のキーワードを確認\n2. 各選択肢を医学的に検討\n3. 正解を選択\n\n最終行に「答え:」に続けて選択肢(a,b,c,d,e)のみを記載してください。",
    "japanese_medical": "あなたは日本の医療制度と臨床医学に精通した専門医です。\n医学の多肢選択問題に回答します。\n\n重要:\n- 日本の診療ガイドラインに基づいて判断\n- 選択肢はa,b,c,d,eのアルファベットで回答\n- 指定された個数を必ず選択\n\n回答形式: a または a,b,c（複数の場合）"
  }
}