{
  "timestamp": "2026-02-08T14:46:03.749790",
  "model": "mistral-large-instruct-2407",
  "summary": [
    {
      "prompt_key": "baseline",
      "prompt_name": "Baseline (現行)",
      "total": 75,
      "correct": 58,
      "accuracy": 0.7733333333333333,
      "avg_time": 6.2899264717102055,
      "errors": 0,
      "empty_responses": 0
    }
  ],
  "details": {
    "baseline": [
      {
        "problem_id": "116A1",
        "prediction": "c",
        "gold": "c",
        "correct": true,
        "response": "c",
        "time": 7.874469757080078
      },
      {
        "problem_id": "116A2",
        "prediction": "c",
        "gold": "c",
        "correct": true,
        "response": "c",
        "time": 3.6869282722473145
      },
      {
        "problem_id": "116A3",
        "prediction": "a",
        "gold": "a",
        "correct": true,
        "response": "a",
        "time": 3.404764175415039
      },
      {
        "problem_id": "116A4",
        "prediction": "d",
        "gold": "d",
        "correct": true,
        "response": "d",
        "time": 2.3851370811462402
      },
      {
        "problem_id": "116A5",
        "prediction": "c",
        "gold": "c",
        "correct": true,
        "response": "c",
        "time": 3.368586778640747
      },
      {
        "problem_id": "116A6",
        "prediction": "e",
        "gold": "e",
        "correct": true,
        "response": "e",
        "time": 2.4475762844085693
      },
      {
        "problem_id": "116A7",
        "prediction": "d",
        "gold": "d",
        "correct": true,
        "response": "d",
        "time": 2.3885788917541504
      },
      {
        "problem_id": "116A8",
        "prediction": "d",
        "gold": "d",
        "correct": true,
        "response": "d",
        "time": 2.8367340564727783
      },
      {
        "problem_id": "116A9",
        "prediction": "d",
        "gold": "d",
        "correct": true,
        "response": "d",
        "time": 2.3279261589050293
      },
      {
        "problem_id": "116A10",
        "prediction": "d",
        "gold": "d",
        "correct": true,
        "response": "d",
        "time": 2.9074831008911133
      },
      {
        "problem_id": "116A11",
        "prediction": "e",
        "gold": "e",
        "correct": true,
        "response": "e",
        "time": 2.8762731552124023
      },
      {
        "problem_id": "116A12",
        "prediction": "e",
        "gold": "e",
        "correct": true,
        "response": "e",
        "time": 3.355652093887329
      },
      {
        "problem_id": "116A13",
        "prediction": "b,e",
        "gold": "b,e",
        "correct": true,
        "response": "b,e",
        "time": 3.760118007659912
      },
      {
        "problem_id": "116A14",
        "prediction": "c,d",
        "gold": "c,d",
        "correct": true,
        "response": "c,d",
        "time": 3.733342170715332
      },
      {
        "problem_id": "116A15",
        "prediction": "c,e",
        "gold": "c,e",
        "correct": true,
        "response": "c,e",
        "time": 2.7475860118865967
      },
      {
        "problem_id": "116A16",
        "prediction": "c",
        "gold": "c",
        "correct": true,
        "response": "c",
        "time": 10.565260887145996
      },
      {
        "problem_id": "116A17",
        "prediction": "e",
        "gold": "e",
        "correct": true,
        "response": "e",
        "time": 7.900416135787964
      },
      {
        "problem_id": "116A18",
        "prediction": "c",
        "gold": "a",
        "correct": false,
        "response": "c",
        "time": 5.117128849029541
      },
      {
        "problem_id": "116A19",
        "prediction": "d",
        "gold": "d",
        "correct": true,
        "response": "d",
        "time": 7.204146385192871
      },
      {
        "problem_id": "116A20",
        "prediction": "b",
        "gold": "b",
        "correct": true,
        "response": "b",
        "time": 6.456374168395996
      },
      {
        "problem_id": "116A21",
        "prediction": "b",
        "gold": "c",
        "correct": false,
        "response": "b",
        "time": 7.016680955886841
      },
      {
        "problem_id": "116A22",
        "prediction": "c",
        "gold": "c",
        "correct": true,
        "response": "c",
        "time": 4.812258005142212
      },
      {
        "problem_id": "116A23",
        "prediction": "a",
        "gold": "e",
        "correct": false,
        "response": "a",
        "time": 8.663779258728027
      },
      {
        "problem_id": "116A24",
        "prediction": "c",
        "gold": "c",
        "correct": true,
        "response": "c",
        "time": 3.736156940460205
      },
      {
        "problem_id": "116A25",
        "prediction": "c",
        "gold": "c",
        "correct": true,
        "response": "c",
        "time": 7.050210952758789
      },
      {
        "problem_id": "116A26",
        "prediction": "e",
        "gold": "e",
        "correct": true,
        "response": "e",
        "time": 6.419486045837402
      },
      {
        "problem_id": "116A27",
        "prediction": "b",
        "gold": "b",
        "correct": true,
        "response": "b",
        "time": 7.045190811157227
      },
      {
        "problem_id": "116A28",
        "prediction": "a",
        "gold": "a",
        "correct": true,
        "response": "a",
        "time": 9.470849990844727
      },
      {
        "problem_id": "116A29",
        "prediction": "a",
        "gold": "a",
        "correct": true,
        "response": "a",
        "time": 5.1287150382995605
      },
      {
        "problem_id": "116A30",
        "prediction": "a",
        "gold": "a",
        "correct": true,
        "response": "a",
        "time": 6.12267279624939
      },
      {
        "problem_id": "116A31",
        "prediction": "b",
        "gold": "b",
        "correct": true,
        "response": "b",
        "time": 6.77243185043335
      },
      {
        "problem_id": "116A32",
        "prediction": "e",
        "gold": "e",
        "correct": true,
        "response": "e",
        "time": 6.09112286567688
      },
      {
        "problem_id": "116A33",
        "prediction": "e",
        "gold": "e",
        "correct": true,
        "response": "e",
        "time": 9.626307010650635
      },
      {
        "problem_id": "116A34",
        "prediction": "a",
        "gold": "a",
        "correct": true,
        "response": "a",
        "time": 4.791551828384399
      },
      {
        "problem_id": "116A35",
        "prediction": "e",
        "gold": "e",
        "correct": true,
        "response": "e",
        "time": 7.033340930938721
      },
      {
        "problem_id": "116A36",
        "prediction": "a",
        "gold": "a",
        "correct": true,
        "response": "a",
        "time": 10.441931009292603
      },
      {
        "problem_id": "116A37",
        "prediction": "c",
        "gold": "c",
        "correct": true,
        "response": "c",
        "time": 9.050031661987305
      },
      {
        "problem_id": "116A38",
        "prediction": "e",
        "gold": "e",
        "correct": true,
        "response": "e",
        "time": 9.130146026611328
      },
      {
        "problem_id": "116A39",
        "prediction": "b",
        "gold": "b",
        "correct": true,
        "response": "b",
        "time": 5.27012825012207
      },
      {
        "problem_id": "116A40",
        "prediction": "b",
        "gold": "b",
        "correct": true,
        "response": "b",
        "time": 10.75632905960083
      },
      {
        "problem_id": "116A41",
        "prediction": "e",
        "gold": "e",
        "correct": true,
        "response": "e",
        "time": 4.1210150718688965
      },
      {
        "problem_id": "116A42",
        "prediction": "a",
        "gold": "a",
        "correct": true,
        "response": "a",
        "time": 5.307500123977661
      },
      {
        "problem_id": "116A43",
        "prediction": "c",
        "gold": "c",
        "correct": true,
        "response": "c",
        "time": 8.751864194869995
      },
      {
        "problem_id": "116A44",
        "prediction": "e",
        "gold": "e",
        "correct": true,
        "response": "e",
        "time": 6.081731081008911
      },
      {
        "problem_id": "116A45",
        "prediction": "b",
        "gold": "d",
        "correct": false,
        "response": "b",
        "time": 4.186996936798096
      },
      {
        "problem_id": "116A46",
        "prediction": "e",
        "gold": "b",
        "correct": false,
        "response": "e",
        "time": 6.395601987838745
      },
      {
        "problem_id": "116A47",
        "prediction": "d",
        "gold": "e",
        "correct": false,
        "response": "d",
        "time": 4.545122861862183
      },
      {
        "problem_id": "116A48",
        "prediction": "e",
        "gold": "e",
        "correct": true,
        "response": "e",
        "time": 7.417654037475586
      },
      {
        "problem_id": "116A49",
        "prediction": "a",
        "gold": "a",
        "correct": true,
        "response": "a",
        "time": 8.74503493309021
      },
      {
        "problem_id": "116A50",
        "prediction": "a",
        "gold": "a",
        "correct": true,
        "response": "a",
        "time": 8.65305495262146
      },
      {
        "problem_id": "116A51",
        "prediction": "b",
        "gold": "c",
        "correct": false,
        "response": "b",
        "time": 6.253100872039795
      },
      {
        "problem_id": "116A52",
        "prediction": "d",
        "gold": "d",
        "correct": true,
        "response": "d",
        "time": 3.783876895904541
      },
      {
        "problem_id": "116A53",
        "prediction": "b",
        "gold": "b",
        "correct": true,
        "response": "b",
        "time": 7.773024082183838
      },
      {
        "problem_id": "116A54",
        "prediction": "e",
        "gold": "e",
        "correct": true,
        "response": "e",
        "time": 5.065699815750122
      },
      {
        "problem_id": "116A55",
        "prediction": "e",
        "gold": "e",
        "correct": true,
        "response": "e",
        "time": 5.07560396194458
      },
      {
        "problem_id": "116A56",
        "prediction": "b",
        "gold": "b",
        "correct": true,
        "response": "b",
        "time": 9.249657154083252
      },
      {
        "problem_id": "116A57",
        "prediction": "a",
        "gold": "a",
        "correct": true,
        "response": "a",
        "time": 6.691324949264526
      },
      {
        "problem_id": "116A58",
        "prediction": "b",
        "gold": "b",
        "correct": true,
        "response": "b",
        "time": 4.293527126312256
      },
      {
        "problem_id": "116A59",
        "prediction": "d",
        "gold": "c",
        "correct": false,
        "response": "d",
        "time": 5.231934070587158
      },
      {
        "problem_id": "116A60",
        "prediction": "b",
        "gold": "a",
        "correct": false,
        "response": "b",
        "time": 5.487673759460449
      },
      {
        "problem_id": "116A61",
        "prediction": "a",
        "gold": "a",
        "correct": true,
        "response": "a",
        "time": 3.968956232070923
      },
      {
        "problem_id": "116A62",
        "prediction": "a",
        "gold": "a",
        "correct": true,
        "response": "a",
        "time": 11.943277835845947
      },
      {
        "problem_id": "116A63",
        "prediction": "e",
        "gold": "e",
        "correct": true,
        "response": "e",
        "time": 6.313807725906372
      },
      {
        "problem_id": "116A64",
        "prediction": "e",
        "gold": "e",
        "correct": true,
        "response": "e",
        "time": 6.347341060638428
      },
      {
        "problem_id": "116A65",
        "prediction": "b,c",
        "gold": "b,e",
        "correct": false,
        "response": "b,c",
        "time": 7.877063274383545
      },
      {
        "problem_id": "116A66",
        "prediction": "c,d",
        "gold": "a,e",
        "correct": false,
        "response": "c,d",
        "time": 5.183345794677734
      },
      {
        "problem_id": "116A67",
        "prediction": "b,d",
        "gold": "a,d",
        "correct": false,
        "response": "b,d",
        "time": 7.256781816482544
      },
      {
        "problem_id": "116A68",
        "prediction": "b,d",
        "gold": "d,e",
        "correct": false,
        "response": "b,d",
        "time": 8.073244094848633
      },
      {
        "problem_id": "116A69",
        "prediction": "b,c",
        "gold": "a,b",
        "correct": false,
        "response": "b,c",
        "time": 6.258596897125244
      },
      {
        "problem_id": "116A70",
        "prediction": "b,d",
        "gold": "b,e",
        "correct": false,
        "response": "b,d",
        "time": 11.432411909103394
      },
      {
        "problem_id": "116A71",
        "prediction": "a",
        "gold": "e",
        "correct": false,
        "response": "a",
        "time": 6.134602069854736
      },
      {
        "problem_id": "116A72",
        "prediction": "a,b,d",
        "gold": "a,b,d",
        "correct": true,
        "response": "a,b,d",
        "time": 8.613816022872925
      },
      {
        "problem_id": "116A73",
        "prediction": "a,c,d",
        "gold": "a,c,e",
        "correct": false,
        "response": "a,c,d",
        "time": 9.488121032714844
      },
      {
        "problem_id": "116A74",
        "prediction": "a,b,d",
        "gold": "a,b,d",
        "correct": true,
        "response": "a,b,d",
        "time": 8.994888067245483
      },
      {
        "problem_id": "116A75",
        "prediction": "a,c,d",
        "gold": "a,c,d",
        "correct": true,
        "response": "a,c,d",
        "time": 8.973428964614868
      }
    ]
  },
  "prompts": {
    "baseline": "あなたは医学の専門家です。選択肢から正解をa,b,c,d,eで答えてください。",
    "format_strict": "あなたは臨床医学に精通した医師です。\n問題を読み、正解の選択肢をアルファベット(a,b,c,d,e)のみで回答してください。\n複数選択の場合はカンマ区切りで回答してください。例: a,c\n余計な説明は不要です。",
    "chain_of_thought": "あなたは臨床医学に精通した医師です。\n\n回答手順:\n1. 問題文のキーワードを確認\n2. 各選択肢を医学的に検討\n3. 正解を選択\n\n最終行に「答え:」に続けて選択肢(a,b,c,d,e)のみを記載してください。",
    "japanese_medical": "あなたは日本の医療制度と臨床医学に精通した専門医です。\n医学の多肢選択問題に回答します。\n\n重要:\n- 日本の診療ガイドラインに基づいて判断\n- 選択肢はa,b,c,d,eのアルファベットで回答\n- 指定された個数を必ず選択\n\n回答形式: a または a,b,c（複数の場合）"
  }
}